{
  "links": [
    {
      "url": {
        "protocol": "https:",
        "slashes": true,
        "auth": null,
        "host": "monsuivisocial.incubateur.anct.gouv.fr",
        "port": null,
        "hostname": "monsuivisocial.incubateur.anct.gouv.fr",
        "hash": null,
        "search": null,
        "query": null,
        "pathname": "/",
        "path": "/",
        "href": "https://monsuivisocial.incubateur.anct.gouv.fr/"
      },
      "link": "https://monsuivisocial.incubateur.anct.gouv.fr/",
      "line": "--2024-07-21 01:29:05--  https://monsuivisocial.incubateur.anct.gouv.fr/",
      "broken": false
    },
    {
      "url": {
        "protocol": "https:",
        "slashes": true,
        "auth": null,
        "host": "monsuivisocial.incubateur.anct.gouv.fr",
        "port": null,
        "hostname": "monsuivisocial.incubateur.anct.gouv.fr",
        "hash": null,
        "search": null,
        "query": null,
        "pathname": "/robots.txt",
        "path": "/robots.txt",
        "href": "https://monsuivisocial.incubateur.anct.gouv.fr/robots.txt"
      },
      "link": "https://monsuivisocial.incubateur.anct.gouv.fr/robots.txt",
      "line": "--2024-07-21 01:29:06--  https://monsuivisocial.incubateur.anct.gouv.fr/robots.txt",
      "broken": false
    },
    {
      "url": {
        "protocol": "https:",
        "slashes": true,
        "auth": null,
        "host": "monsuivisocial.incubateur.anct.gouv.fr",
        "port": null,
        "hostname": "monsuivisocial.incubateur.anct.gouv.fr",
        "hash": null,
        "search": null,
        "query": null,
        "pathname": "/favicon.ico",
        "path": "/favicon.ico",
        "href": "https://monsuivisocial.incubateur.anct.gouv.fr/favicon.ico"
      },
      "link": "https://monsuivisocial.incubateur.anct.gouv.fr/favicon.ico",
      "line": "--2024-07-21 01:29:06--  https://monsuivisocial.incubateur.anct.gouv.fr/favicon.ico",
      "broken": false
    },
    {
      "url": {
        "protocol": "https:",
        "slashes": true,
        "auth": null,
        "host": "monsuivisocial.incubateur.anct.gouv.fr",
        "port": null,
        "hostname": "monsuivisocial.incubateur.anct.gouv.fr",
        "hash": null,
        "search": null,
        "query": null,
        "pathname": "/favicon.svg",
        "path": "/favicon.svg",
        "href": "https://monsuivisocial.incubateur.anct.gouv.fr/favicon.svg"
      },
      "link": "https://monsuivisocial.incubateur.anct.gouv.fr/favicon.svg",
      "line": "--2024-07-21 01:29:07--  https://monsuivisocial.incubateur.anct.gouv.fr/favicon.svg",
      "broken": false
    },
    {
      "url": {
        "protocol": "https:",
        "slashes": true,
        "auth": null,
        "host": "monsuivisocial.incubateur.anct.gouv.fr",
        "port": null,
        "hostname": "monsuivisocial.incubateur.anct.gouv.fr",
        "hash": null,
        "search": null,
        "query": null,
        "pathname": "/apple-touch-favicon.png",
        "path": "/apple-touch-favicon.png",
        "href": "https://monsuivisocial.incubateur.anct.gouv.fr/apple-touch-favicon.png"
      },
      "link": "https://monsuivisocial.incubateur.anct.gouv.fr/apple-touch-favicon.png",
      "line": "--2024-07-21 01:29:07--  https://monsuivisocial.incubateur.anct.gouv.fr/apple-touch-favicon.png",
      "broken": false
    },
    {
      "url": {
        "protocol": "https:",
        "slashes": true,
        "auth": null,
        "host": "monsuivisocial.incubateur.anct.gouv.fr",
        "port": null,
        "hostname": "monsuivisocial.incubateur.anct.gouv.fr",
        "hash": null,
        "search": null,
        "query": null,
        "pathname": "/manifest.webmanifest",
        "path": "/manifest.webmanifest",
        "href": "https://monsuivisocial.incubateur.anct.gouv.fr/manifest.webmanifest"
      },
      "link": "https://monsuivisocial.incubateur.anct.gouv.fr/manifest.webmanifest",
      "line": "--2024-07-21 01:29:07--  https://monsuivisocial.incubateur.anct.gouv.fr/manifest.webmanifest",
      "broken": false
    },
    {
      "url": {
        "protocol": "https:",
        "slashes": true,
        "auth": null,
        "host": "monsuivisocial.incubateur.anct.gouv.fr",
        "port": null,
        "hostname": "monsuivisocial.incubateur.anct.gouv.fr",
        "hash": null,
        "search": null,
        "query": null,
        "pathname": "/_nuxt/Marianne-Light.DsZfzyg9.woff2",
        "path": "/_nuxt/Marianne-Light.DsZfzyg9.woff2",
        "href": "https://monsuivisocial.incubateur.anct.gouv.fr/_nuxt/Marianne-Light.DsZfzyg9.woff2"
      },
      "link": "https://monsuivisocial.incubateur.anct.gouv.fr/_nuxt/Marianne-Light.DsZfzyg9.woff2",
      "line": "--2024-07-21 01:29:07--  https://monsuivisocial.incubateur.anct.gouv.fr/_nuxt/Marianne-Light.DsZfzyg9.woff2",
      "broken": false
    },
    {
      "url": {
        "protocol": "https:",
        "slashes": true,
        "auth": null,
        "host": "monsuivisocial.incubateur.anct.gouv.fr",
        "port": null,
        "hostname": "monsuivisocial.incubateur.anct.gouv.fr",
        "hash": null,
        "search": null,
        "query": null,
        "pathname": "/_nuxt/Marianne-Light.DqWaxKdz.woff",
        "path": "/_nuxt/Marianne-Light.DqWaxKdz.woff",
        "href": "https://monsuivisocial.incubateur.anct.gouv.fr/_nuxt/Marianne-Light.DqWaxKdz.woff"
      },
      "link": "https://monsuivisocial.incubateur.anct.gouv.fr/_nuxt/Marianne-Light.DqWaxKdz.woff",
      "line": "--2024-07-21 01:29:07--  https://monsuivisocial.incubateur.anct.gouv.fr/_nuxt/Marianne-Light.DqWaxKdz.woff",
      "broken": false
    },
    {
      "url": {
        "protocol": "https:",
        "slashes": true,
        "auth": null,
        "host": "monsuivisocial.incubateur.anct.gouv.fr",
        "port": null,
        "hostname": "monsuivisocial.incubateur.anct.gouv.fr",
        "hash": null,
        "search": null,
        "query": null,
        "pathname": "/_nuxt/Marianne-Light_Italic.Yne2G_jl.woff2",
        "path": "/_nuxt/Marianne-Light_Italic.Yne2G_jl.woff2",
        "href": "https://monsuivisocial.incubateur.anct.gouv.fr/_nuxt/Marianne-Light_Italic.Yne2G_jl.woff2"
      },
      "link": "https://monsuivisocial.incubateur.anct.gouv.fr/_nuxt/Marianne-Light_Italic.Yne2G_jl.woff2",
      "line": "--2024-07-21 01:29:07--  https://monsuivisocial.incubateur.anct.gouv.fr/_nuxt/Marianne-Light_Italic.Yne2G_jl.woff2",
      "broken": false
    },
    {
      "url": {
        "protocol": "https:",
        "slashes": true,
        "auth": null,
        "host": "monsuivisocial.incubateur.anct.gouv.fr",
        "port": null,
        "hostname": "monsuivisocial.incubateur.anct.gouv.fr",
        "hash": null,
        "search": null,
        "query": null,
        "pathname": "/_nuxt/Marianne-Light_Italic.BJOCXSxu.woff",
        "path": "/_nuxt/Marianne-Light_Italic.BJOCXSxu.woff",
        "href": "https://monsuivisocial.incubateur.anct.gouv.fr/_nuxt/Marianne-Light_Italic.BJOCXSxu.woff"
      },
      "link": "https://monsuivisocial.incubateur.anct.gouv.fr/_nuxt/Marianne-Light_Italic.BJOCXSxu.woff",
      "line": "--2024-07-21 01:29:07--  https://monsuivisocial.incubateur.anct.gouv.fr/_nuxt/Marianne-Light_Italic.BJOCXSxu.woff",
      "broken": false
    },
    {
      "url": {
        "protocol": "https:",
        "slashes": true,
        "auth": null,
        "host": "monsuivisocial.incubateur.anct.gouv.fr",
        "port": null,
        "hostname": "monsuivisocial.incubateur.anct.gouv.fr",
        "hash": null,
        "search": null,
        "query": null,
        "pathname": "/_nuxt/Marianne-Regular.CaCqrnJM.woff2",
        "path": "/_nuxt/Marianne-Regular.CaCqrnJM.woff2",
        "href": "https://monsuivisocial.incubateur.anct.gouv.fr/_nuxt/Marianne-Regular.CaCqrnJM.woff2"
      },
      "link": "https://monsuivisocial.incubateur.anct.gouv.fr/_nuxt/Marianne-Regular.CaCqrnJM.woff2",
      "line": "--2024-07-21 01:29:07--  https://monsuivisocial.incubateur.anct.gouv.fr/_nuxt/Marianne-Regular.CaCqrnJM.woff2",
      "broken": false
    },
    {
      "url": {
        "protocol": "https:",
        "slashes": true,
        "auth": null,
        "host": "monsuivisocial.incubateur.anct.gouv.fr",
        "port": null,
        "hostname": "monsuivisocial.incubateur.anct.gouv.fr",
        "hash": null,
        "search": null,
        "query": null,
        "pathname": "/_nuxt/Marianne-Regular.DxIeSxmB.woff",
        "path": "/_nuxt/Marianne-Regular.DxIeSxmB.woff",
        "href": "https://monsuivisocial.incubateur.anct.gouv.fr/_nuxt/Marianne-Regular.DxIeSxmB.woff"
      },
      "link": "https://monsuivisocial.incubateur.anct.gouv.fr/_nuxt/Marianne-Regular.DxIeSxmB.woff",
      "line": "--2024-07-21 01:29:07--  https://monsuivisocial.incubateur.anct.gouv.fr/_nuxt/Marianne-Regular.DxIeSxmB.woff",
      "broken": false
    },
    {
      "url": {
        "protocol": "https:",
        "slashes": true,
        "auth": null,
        "host": "monsuivisocial.incubateur.anct.gouv.fr",
        "port": null,
        "hostname": "monsuivisocial.incubateur.anct.gouv.fr",
        "hash": null,
        "search": null,
        "query": null,
        "pathname": "/_nuxt/Marianne-Regular_Italic.DdH8FtNo.woff2",
        "path": "/_nuxt/Marianne-Regular_Italic.DdH8FtNo.woff2",
        "href": "https://monsuivisocial.incubateur.anct.gouv.fr/_nuxt/Marianne-Regular_Italic.DdH8FtNo.woff2"
      },
      "link": "https://monsuivisocial.incubateur.anct.gouv.fr/_nuxt/Marianne-Regular_Italic.DdH8FtNo.woff2",
      "line": "--2024-07-21 01:29:08--  https://monsuivisocial.incubateur.anct.gouv.fr/_nuxt/Marianne-Regular_Italic.DdH8FtNo.woff2",
      "broken": false
    },
    {
      "url": {
        "protocol": "https:",
        "slashes": true,
        "auth": null,
        "host": "monsuivisocial.incubateur.anct.gouv.fr",
        "port": null,
        "hostname": "monsuivisocial.incubateur.anct.gouv.fr",
        "hash": null,
        "search": null,
        "query": null,
        "pathname": "/_nuxt/Marianne-Regular_Italic.BQJsTSNr.woff",
        "path": "/_nuxt/Marianne-Regular_Italic.BQJsTSNr.woff",
        "href": "https://monsuivisocial.incubateur.anct.gouv.fr/_nuxt/Marianne-Regular_Italic.BQJsTSNr.woff"
      },
      "link": "https://monsuivisocial.incubateur.anct.gouv.fr/_nuxt/Marianne-Regular_Italic.BQJsTSNr.woff",
      "line": "--2024-07-21 01:29:08--  https://monsuivisocial.incubateur.anct.gouv.fr/_nuxt/Marianne-Regular_Italic.BQJsTSNr.woff",
      "broken": false
    },
    {
      "url": {
        "protocol": "https:",
        "slashes": true,
        "auth": null,
        "host": "monsuivisocial.incubateur.anct.gouv.fr",
        "port": null,
        "hostname": "monsuivisocial.incubateur.anct.gouv.fr",
        "hash": null,
        "search": null,
        "query": null,
        "pathname": "/_nuxt/Marianne-Medium.DptVAR1p.woff2",
        "path": "/_nuxt/Marianne-Medium.DptVAR1p.woff2",
        "href": "https://monsuivisocial.incubateur.anct.gouv.fr/_nuxt/Marianne-Medium.DptVAR1p.woff2"
      },
      "link": "https://monsuivisocial.incubateur.anct.gouv.fr/_nuxt/Marianne-Medium.DptVAR1p.woff2",
      "line": "--2024-07-21 01:29:08--  https://monsuivisocial.incubateur.anct.gouv.fr/_nuxt/Marianne-Medium.DptVAR1p.woff2",
      "broken": false
    },
    {
      "url": {
        "protocol": "https:",
        "slashes": true,
        "auth": null,
        "host": "monsuivisocial.incubateur.anct.gouv.fr",
        "port": null,
        "hostname": "monsuivisocial.incubateur.anct.gouv.fr",
        "hash": null,
        "search": null,
        "query": null,
        "pathname": "/_nuxt/Marianne-Medium.CmsIrdJJ.woff",
        "path": "/_nuxt/Marianne-Medium.CmsIrdJJ.woff",
        "href": "https://monsuivisocial.incubateur.anct.gouv.fr/_nuxt/Marianne-Medium.CmsIrdJJ.woff"
      },
      "link": "https://monsuivisocial.incubateur.anct.gouv.fr/_nuxt/Marianne-Medium.CmsIrdJJ.woff",
      "line": "--2024-07-21 01:29:08--  https://monsuivisocial.incubateur.anct.gouv.fr/_nuxt/Marianne-Medium.CmsIrdJJ.woff",
      "broken": false
    },
    {
      "url": {
        "protocol": "https:",
        "slashes": true,
        "auth": null,
        "host": "monsuivisocial.incubateur.anct.gouv.fr",
        "port": null,
        "hostname": "monsuivisocial.incubateur.anct.gouv.fr",
        "hash": null,
        "search": null,
        "query": null,
        "pathname": "/_nuxt/Marianne-Medium_Italic.WqZFT7wM.woff2",
        "path": "/_nuxt/Marianne-Medium_Italic.WqZFT7wM.woff2",
        "href": "https://monsuivisocial.incubateur.anct.gouv.fr/_nuxt/Marianne-Medium_Italic.WqZFT7wM.woff2"
      },
      "link": "https://monsuivisocial.incubateur.anct.gouv.fr/_nuxt/Marianne-Medium_Italic.WqZFT7wM.woff2",
      "line": "--2024-07-21 01:29:08--  https://monsuivisocial.incubateur.anct.gouv.fr/_nuxt/Marianne-Medium_Italic.WqZFT7wM.woff2",
      "broken": false
    },
    {
      "url": {
        "protocol": "https:",
        "slashes": true,
        "auth": null,
        "host": "monsuivisocial.incubateur.anct.gouv.fr",
        "port": null,
        "hostname": "monsuivisocial.incubateur.anct.gouv.fr",
        "hash": null,
        "search": null,
        "query": null,
        "pathname": "/_nuxt/Marianne-Medium_Italic.BP8MGzkr.woff",
        "path": "/_nuxt/Marianne-Medium_Italic.BP8MGzkr.woff",
        "href": "https://monsuivisocial.incubateur.anct.gouv.fr/_nuxt/Marianne-Medium_Italic.BP8MGzkr.woff"
      },
      "link": "https://monsuivisocial.incubateur.anct.gouv.fr/_nuxt/Marianne-Medium_Italic.BP8MGzkr.woff",
      "line": "--2024-07-21 01:29:08--  https://monsuivisocial.incubateur.anct.gouv.fr/_nuxt/Marianne-Medium_Italic.BP8MGzkr.woff",
      "broken": false
    },
    {
      "url": {
        "protocol": "https:",
        "slashes": true,
        "auth": null,
        "host": "monsuivisocial.incubateur.anct.gouv.fr",
        "port": null,
        "hostname": "monsuivisocial.incubateur.anct.gouv.fr",
        "hash": null,
        "search": null,
        "query": null,
        "pathname": "/_nuxt/Marianne-Bold.CYjThbH0.woff2",
        "path": "/_nuxt/Marianne-Bold.CYjThbH0.woff2",
        "href": "https://monsuivisocial.incubateur.anct.gouv.fr/_nuxt/Marianne-Bold.CYjThbH0.woff2"
      },
      "link": "https://monsuivisocial.incubateur.anct.gouv.fr/_nuxt/Marianne-Bold.CYjThbH0.woff2",
      "line": "--2024-07-21 01:29:08--  https://monsuivisocial.incubateur.anct.gouv.fr/_nuxt/Marianne-Bold.CYjThbH0.woff2",
      "broken": false
    },
    {
      "url": {
        "protocol": "https:",
        "slashes": true,
        "auth": null,
        "host": "monsuivisocial.incubateur.anct.gouv.fr",
        "port": null,
        "hostname": "monsuivisocial.incubateur.anct.gouv.fr",
        "hash": null,
        "search": null,
        "query": null,
        "pathname": "/_nuxt/Marianne-Bold.u6yfe4-h.woff",
        "path": "/_nuxt/Marianne-Bold.u6yfe4-h.woff",
        "href": "https://monsuivisocial.incubateur.anct.gouv.fr/_nuxt/Marianne-Bold.u6yfe4-h.woff"
      },
      "link": "https://monsuivisocial.incubateur.anct.gouv.fr/_nuxt/Marianne-Bold.u6yfe4-h.woff",
      "line": "--2024-07-21 01:29:08--  https://monsuivisocial.incubateur.anct.gouv.fr/_nuxt/Marianne-Bold.u6yfe4-h.woff",
      "broken": false
    },
    {
      "url": {
        "protocol": "https:",
        "slashes": true,
        "auth": null,
        "host": "monsuivisocial.incubateur.anct.gouv.fr",
        "port": null,
        "hostname": "monsuivisocial.incubateur.anct.gouv.fr",
        "hash": null,
        "search": null,
        "query": null,
        "pathname": "/_nuxt/Marianne-Bold_Italic.BqW9V1Nh.woff2",
        "path": "/_nuxt/Marianne-Bold_Italic.BqW9V1Nh.woff2",
        "href": "https://monsuivisocial.incubateur.anct.gouv.fr/_nuxt/Marianne-Bold_Italic.BqW9V1Nh.woff2"
      },
      "link": "https://monsuivisocial.incubateur.anct.gouv.fr/_nuxt/Marianne-Bold_Italic.BqW9V1Nh.woff2",
      "line": "--2024-07-21 01:29:08--  https://monsuivisocial.incubateur.anct.gouv.fr/_nuxt/Marianne-Bold_Italic.BqW9V1Nh.woff2",
      "broken": false
    },
    {
      "url": {
        "protocol": "https:",
        "slashes": true,
        "auth": null,
        "host": "monsuivisocial.incubateur.anct.gouv.fr",
        "port": null,
        "hostname": "monsuivisocial.incubateur.anct.gouv.fr",
        "hash": null,
        "search": null,
        "query": null,
        "pathname": "/_nuxt/Marianne-Bold_Italic.BWnPOpjP.woff",
        "path": "/_nuxt/Marianne-Bold_Italic.BWnPOpjP.woff",
        "href": "https://monsuivisocial.incubateur.anct.gouv.fr/_nuxt/Marianne-Bold_Italic.BWnPOpjP.woff"
      },
      "link": "https://monsuivisocial.incubateur.anct.gouv.fr/_nuxt/Marianne-Bold_Italic.BWnPOpjP.woff",
      "line": "--2024-07-21 01:29:08--  https://monsuivisocial.incubateur.anct.gouv.fr/_nuxt/Marianne-Bold_Italic.BWnPOpjP.woff",
      "broken": false
    },
    {
      "url": {
        "protocol": "https:",
        "slashes": true,
        "auth": null,
        "host": "monsuivisocial.incubateur.anct.gouv.fr",
        "port": null,
        "hostname": "monsuivisocial.incubateur.anct.gouv.fr",
        "hash": null,
        "search": null,
        "query": null,
        "pathname": "/_nuxt/Spectral-Regular.PmBQicsR.woff2",
        "path": "/_nuxt/Spectral-Regular.PmBQicsR.woff2",
        "href": "https://monsuivisocial.incubateur.anct.gouv.fr/_nuxt/Spectral-Regular.PmBQicsR.woff2"
      },
      "link": "https://monsuivisocial.incubateur.anct.gouv.fr/_nuxt/Spectral-Regular.PmBQicsR.woff2",
      "line": "--2024-07-21 01:29:08--  https://monsuivisocial.incubateur.anct.gouv.fr/_nuxt/Spectral-Regular.PmBQicsR.woff2",
      "broken": false
    },
    {
      "url": {
        "protocol": "https:",
        "slashes": true,
        "auth": null,
        "host": "monsuivisocial.incubateur.anct.gouv.fr",
        "port": null,
        "hostname": "monsuivisocial.incubateur.anct.gouv.fr",
        "hash": null,
        "search": null,
        "query": null,
        "pathname": "/_nuxt/Spectral-Regular.D0Iocl0n.woff",
        "path": "/_nuxt/Spectral-Regular.D0Iocl0n.woff",
        "href": "https://monsuivisocial.incubateur.anct.gouv.fr/_nuxt/Spectral-Regular.D0Iocl0n.woff"
      },
      "link": "https://monsuivisocial.incubateur.anct.gouv.fr/_nuxt/Spectral-Regular.D0Iocl0n.woff",
      "line": "--2024-07-21 01:29:09--  https://monsuivisocial.incubateur.anct.gouv.fr/_nuxt/Spectral-Regular.D0Iocl0n.woff",
      "broken": false
    },
    {
      "url": {
        "protocol": "https:",
        "slashes": true,
        "auth": null,
        "host": "monsuivisocial.incubateur.anct.gouv.fr",
        "port": null,
        "hostname": "monsuivisocial.incubateur.anct.gouv.fr",
        "hash": null,
        "search": null,
        "query": null,
        "pathname": "/_nuxt/Spectral-ExtraBold.CCzfBm-A.woff2",
        "path": "/_nuxt/Spectral-ExtraBold.CCzfBm-A.woff2",
        "href": "https://monsuivisocial.incubateur.anct.gouv.fr/_nuxt/Spectral-ExtraBold.CCzfBm-A.woff2"
      },
      "link": "https://monsuivisocial.incubateur.anct.gouv.fr/_nuxt/Spectral-ExtraBold.CCzfBm-A.woff2",
      "line": "--2024-07-21 01:29:09--  https://monsuivisocial.incubateur.anct.gouv.fr/_nuxt/Spectral-ExtraBold.CCzfBm-A.woff2",
      "broken": false
    },
    {
      "url": {
        "protocol": "https:",
        "slashes": true,
        "auth": null,
        "host": "monsuivisocial.incubateur.anct.gouv.fr",
        "port": null,
        "hostname": "monsuivisocial.incubateur.anct.gouv.fr",
        "hash": null,
        "search": null,
        "query": null,
        "pathname": "/_nuxt/Spectral-ExtraBold.U325s3c2.woff",
        "path": "/_nuxt/Spectral-ExtraBold.U325s3c2.woff",
        "href": "https://monsuivisocial.incubateur.anct.gouv.fr/_nuxt/Spectral-ExtraBold.U325s3c2.woff"
      },
      "link": "https://monsuivisocial.incubateur.anct.gouv.fr/_nuxt/Spectral-ExtraBold.U325s3c2.woff",
      "line": "--2024-07-21 01:29:09--  https://monsuivisocial.incubateur.anct.gouv.fr/_nuxt/Spectral-ExtraBold.U325s3c2.woff",
      "broken": false
    },
    {
      "url": {
        "protocol": "https:",
        "slashes": true,
        "auth": null,
        "host": "monsuivisocial.incubateur.anct.gouv.fr",
        "port": null,
        "hostname": "monsuivisocial.incubateur.anct.gouv.fr",
        "hash": null,
        "search": null,
        "query": null,
        "pathname": "/_nuxt/france-line.COP-qOGW.svg",
        "path": "/_nuxt/france-line.COP-qOGW.svg",
        "href": "https://monsuivisocial.incubateur.anct.gouv.fr/_nuxt/france-line.COP-qOGW.svg"
      },
      "link": "https://monsuivisocial.incubateur.anct.gouv.fr/_nuxt/france-line.COP-qOGW.svg",
      "line": "--2024-07-21 01:29:09--  https://monsuivisocial.incubateur.anct.gouv.fr/_nuxt/france-line.COP-qOGW.svg",
      "broken": false
    },
    {
      "url": {
        "protocol": "https:",
        "slashes": true,
        "auth": null,
        "host": "monsuivisocial.incubateur.anct.gouv.fr",
        "port": null,
        "hostname": "monsuivisocial.incubateur.anct.gouv.fr",
        "hash": null,
        "search": null,
        "query": null,
        "pathname": "/_nuxt/home-contact.hPTpHRVR.svg",
        "path": "/_nuxt/home-contact.hPTpHRVR.svg",
        "href": "https://monsuivisocial.incubateur.anct.gouv.fr/_nuxt/home-contact.hPTpHRVR.svg"
      },
      "link": "https://monsuivisocial.incubateur.anct.gouv.fr/_nuxt/home-contact.hPTpHRVR.svg",
      "line": "--2024-07-21 01:29:09--  https://monsuivisocial.incubateur.anct.gouv.fr/_nuxt/home-contact.hPTpHRVR.svg",
      "broken": false
    },
    {
      "url": {
        "protocol": "https:",
        "slashes": true,
        "auth": null,
        "host": "monsuivisocial.incubateur.anct.gouv.fr",
        "port": null,
        "hostname": "monsuivisocial.incubateur.anct.gouv.fr",
        "hash": null,
        "search": null,
        "query": null,
        "pathname": "/_nuxt/entry.Dp6-5gVF.css",
        "path": "/_nuxt/entry.Dp6-5gVF.css",
        "href": "https://monsuivisocial.incubateur.anct.gouv.fr/_nuxt/entry.Dp6-5gVF.css"
      },
      "link": "https://monsuivisocial.incubateur.anct.gouv.fr/_nuxt/entry.Dp6-5gVF.css",
      "line": "--2024-07-21 01:29:09--  https://monsuivisocial.incubateur.anct.gouv.fr/_nuxt/entry.Dp6-5gVF.css",
      "broken": false
    },
    {
      "url": {
        "protocol": "https:",
        "slashes": true,
        "auth": null,
        "host": "monsuivisocial.incubateur.anct.gouv.fr",
        "port": null,
        "hostname": "monsuivisocial.incubateur.anct.gouv.fr",
        "hash": null,
        "search": null,
        "query": null,
        "pathname": "/_nuxt/AtomSnackbar.BV_bW89u.css",
        "path": "/_nuxt/AtomSnackbar.BV_bW89u.css",
        "href": "https://monsuivisocial.incubateur.anct.gouv.fr/_nuxt/AtomSnackbar.BV_bW89u.css"
      },
      "link": "https://monsuivisocial.incubateur.anct.gouv.fr/_nuxt/AtomSnackbar.BV_bW89u.css",
      "line": "--2024-07-21 01:29:09--  https://monsuivisocial.incubateur.anct.gouv.fr/_nuxt/AtomSnackbar.BV_bW89u.css",
      "broken": false
    },
    {
      "url": {
        "protocol": "https:",
        "slashes": true,
        "auth": null,
        "host": "monsuivisocial.incubateur.anct.gouv.fr",
        "port": null,
        "hostname": "monsuivisocial.incubateur.anct.gouv.fr",
        "hash": null,
        "search": null,
        "query": null,
        "pathname": "/_nuxt/AtomAlert.DpHQuedB.css",
        "path": "/_nuxt/AtomAlert.DpHQuedB.css",
        "href": "https://monsuivisocial.incubateur.anct.gouv.fr/_nuxt/AtomAlert.DpHQuedB.css"
      },
      "link": "https://monsuivisocial.incubateur.anct.gouv.fr/_nuxt/AtomAlert.DpHQuedB.css",
      "line": "--2024-07-21 01:29:09--  https://monsuivisocial.incubateur.anct.gouv.fr/_nuxt/AtomAlert.DpHQuedB.css",
      "broken": false
    },
    {
      "url": {
        "protocol": "https:",
        "slashes": true,
        "auth": null,
        "host": "monsuivisocial.incubateur.anct.gouv.fr",
        "port": null,
        "hostname": "monsuivisocial.incubateur.anct.gouv.fr",
        "hash": null,
        "search": null,
        "query": null,
        "pathname": "/_nuxt/TheLandingVideo.BQOhy7ca.css",
        "path": "/_nuxt/TheLandingVideo.BQOhy7ca.css",
        "href": "https://monsuivisocial.incubateur.anct.gouv.fr/_nuxt/TheLandingVideo.BQOhy7ca.css"
      },
      "link": "https://monsuivisocial.incubateur.anct.gouv.fr/_nuxt/TheLandingVideo.BQOhy7ca.css",
      "line": "--2024-07-21 01:29:10--  https://monsuivisocial.incubateur.anct.gouv.fr/_nuxt/TheLandingVideo.BQOhy7ca.css",
      "broken": false
    },
    {
      "url": {
        "protocol": "https:",
        "slashes": true,
        "auth": null,
        "host": "monsuivisocial.incubateur.anct.gouv.fr",
        "port": null,
        "hostname": "monsuivisocial.incubateur.anct.gouv.fr",
        "hash": null,
        "search": null,
        "query": null,
        "pathname": "/_nuxt/CrMGtJFn.js",
        "path": "/_nuxt/CrMGtJFn.js",
        "href": "https://monsuivisocial.incubateur.anct.gouv.fr/_nuxt/CrMGtJFn.js"
      },
      "link": "https://monsuivisocial.incubateur.anct.gouv.fr/_nuxt/CrMGtJFn.js",
      "line": "--2024-07-21 01:29:10--  https://monsuivisocial.incubateur.anct.gouv.fr/_nuxt/CrMGtJFn.js",
      "broken": false
    },
    {
      "url": {
        "protocol": "https:",
        "slashes": true,
        "auth": null,
        "host": "monsuivisocial.incubateur.anct.gouv.fr",
        "port": null,
        "hostname": "monsuivisocial.incubateur.anct.gouv.fr",
        "hash": null,
        "search": null,
        "query": null,
        "pathname": "/_nuxt/DITDGqZk.js",
        "path": "/_nuxt/DITDGqZk.js",
        "href": "https://monsuivisocial.incubateur.anct.gouv.fr/_nuxt/DITDGqZk.js"
      },
      "link": "https://monsuivisocial.incubateur.anct.gouv.fr/_nuxt/DITDGqZk.js",
      "line": "--2024-07-21 01:29:10--  https://monsuivisocial.incubateur.anct.gouv.fr/_nuxt/DITDGqZk.js",
      "broken": false
    },
    {
      "url": {
        "protocol": "https:",
        "slashes": true,
        "auth": null,
        "host": "monsuivisocial.incubateur.anct.gouv.fr",
        "port": null,
        "hostname": "monsuivisocial.incubateur.anct.gouv.fr",
        "hash": null,
        "search": null,
        "query": null,
        "pathname": "/_nuxt/DlAUqK2U.js",
        "path": "/_nuxt/DlAUqK2U.js",
        "href": "https://monsuivisocial.incubateur.anct.gouv.fr/_nuxt/DlAUqK2U.js"
      },
      "link": "https://monsuivisocial.incubateur.anct.gouv.fr/_nuxt/DlAUqK2U.js",
      "line": "--2024-07-21 01:29:10--  https://monsuivisocial.incubateur.anct.gouv.fr/_nuxt/DlAUqK2U.js",
      "broken": false
    },
    {
      "url": {
        "protocol": "https:",
        "slashes": true,
        "auth": null,
        "host": "monsuivisocial.incubateur.anct.gouv.fr",
        "port": null,
        "hostname": "monsuivisocial.incubateur.anct.gouv.fr",
        "hash": null,
        "search": null,
        "query": null,
        "pathname": "/_nuxt/OBhQ609G.js",
        "path": "/_nuxt/OBhQ609G.js",
        "href": "https://monsuivisocial.incubateur.anct.gouv.fr/_nuxt/OBhQ609G.js"
      },
      "link": "https://monsuivisocial.incubateur.anct.gouv.fr/_nuxt/OBhQ609G.js",
      "line": "--2024-07-21 01:29:10--  https://monsuivisocial.incubateur.anct.gouv.fr/_nuxt/OBhQ609G.js",
      "broken": false
    },
    {
      "url": {
        "protocol": "https:",
        "slashes": true,
        "auth": null,
        "host": "monsuivisocial.incubateur.anct.gouv.fr",
        "port": null,
        "hostname": "monsuivisocial.incubateur.anct.gouv.fr",
        "hash": null,
        "search": null,
        "query": null,
        "pathname": "/_nuxt/B9PxD17x.js",
        "path": "/_nuxt/B9PxD17x.js",
        "href": "https://monsuivisocial.incubateur.anct.gouv.fr/_nuxt/B9PxD17x.js"
      },
      "link": "https://monsuivisocial.incubateur.anct.gouv.fr/_nuxt/B9PxD17x.js",
      "line": "--2024-07-21 01:29:10--  https://monsuivisocial.incubateur.anct.gouv.fr/_nuxt/B9PxD17x.js",
      "broken": false
    },
    {
      "url": {
        "protocol": "https:",
        "slashes": true,
        "auth": null,
        "host": "monsuivisocial.incubateur.anct.gouv.fr",
        "port": null,
        "hostname": "monsuivisocial.incubateur.anct.gouv.fr",
        "hash": null,
        "search": null,
        "query": null,
        "pathname": "/_nuxt/Ddkyzd10.js",
        "path": "/_nuxt/Ddkyzd10.js",
        "href": "https://monsuivisocial.incubateur.anct.gouv.fr/_nuxt/Ddkyzd10.js"
      },
      "link": "https://monsuivisocial.incubateur.anct.gouv.fr/_nuxt/Ddkyzd10.js",
      "line": "--2024-07-21 01:29:10--  https://monsuivisocial.incubateur.anct.gouv.fr/_nuxt/Ddkyzd10.js",
      "broken": false
    },
    {
      "url": {
        "protocol": "https:",
        "slashes": true,
        "auth": null,
        "host": "monsuivisocial.incubateur.anct.gouv.fr",
        "port": null,
        "hostname": "monsuivisocial.incubateur.anct.gouv.fr",
        "hash": null,
        "search": null,
        "query": null,
        "pathname": "/_nuxt/C31km4cq.js",
        "path": "/_nuxt/C31km4cq.js",
        "href": "https://monsuivisocial.incubateur.anct.gouv.fr/_nuxt/C31km4cq.js"
      },
      "link": "https://monsuivisocial.incubateur.anct.gouv.fr/_nuxt/C31km4cq.js",
      "line": "--2024-07-21 01:29:10--  https://monsuivisocial.incubateur.anct.gouv.fr/_nuxt/C31km4cq.js",
      "broken": false
    },
    {
      "url": {
        "protocol": "https:",
        "slashes": true,
        "auth": null,
        "host": "monsuivisocial.incubateur.anct.gouv.fr",
        "port": null,
        "hostname": "monsuivisocial.incubateur.anct.gouv.fr",
        "hash": null,
        "search": null,
        "query": null,
        "pathname": "/_nuxt/Cbt_xw4W.js",
        "path": "/_nuxt/Cbt_xw4W.js",
        "href": "https://monsuivisocial.incubateur.anct.gouv.fr/_nuxt/Cbt_xw4W.js"
      },
      "link": "https://monsuivisocial.incubateur.anct.gouv.fr/_nuxt/Cbt_xw4W.js",
      "line": "--2024-07-21 01:29:10--  https://monsuivisocial.incubateur.anct.gouv.fr/_nuxt/Cbt_xw4W.js",
      "broken": false
    },
    {
      "url": {
        "protocol": "https:",
        "slashes": true,
        "auth": null,
        "host": "monsuivisocial.incubateur.anct.gouv.fr",
        "port": null,
        "hostname": "monsuivisocial.incubateur.anct.gouv.fr",
        "hash": null,
        "search": null,
        "query": null,
        "pathname": "/_nuxt/CgSF-gNA.js",
        "path": "/_nuxt/CgSF-gNA.js",
        "href": "https://monsuivisocial.incubateur.anct.gouv.fr/_nuxt/CgSF-gNA.js"
      },
      "link": "https://monsuivisocial.incubateur.anct.gouv.fr/_nuxt/CgSF-gNA.js",
      "line": "--2024-07-21 01:29:10--  https://monsuivisocial.incubateur.anct.gouv.fr/_nuxt/CgSF-gNA.js",
      "broken": false
    },
    {
      "url": {
        "protocol": "https:",
        "slashes": true,
        "auth": null,
        "host": "monsuivisocial.incubateur.anct.gouv.fr",
        "port": null,
        "hostname": "monsuivisocial.incubateur.anct.gouv.fr",
        "hash": null,
        "search": null,
        "query": null,
        "pathname": "/_nuxt/CrUrv3lG.js",
        "path": "/_nuxt/CrUrv3lG.js",
        "href": "https://monsuivisocial.incubateur.anct.gouv.fr/_nuxt/CrUrv3lG.js"
      },
      "link": "https://monsuivisocial.incubateur.anct.gouv.fr/_nuxt/CrUrv3lG.js",
      "line": "--2024-07-21 01:29:11--  https://monsuivisocial.incubateur.anct.gouv.fr/_nuxt/CrUrv3lG.js",
      "broken": false
    },
    {
      "url": {
        "protocol": "https:",
        "slashes": true,
        "auth": null,
        "host": "monsuivisocial.incubateur.anct.gouv.fr",
        "port": null,
        "hostname": "monsuivisocial.incubateur.anct.gouv.fr",
        "hash": null,
        "search": null,
        "query": null,
        "pathname": "/_nuxt/D1qks5nO.js",
        "path": "/_nuxt/D1qks5nO.js",
        "href": "https://monsuivisocial.incubateur.anct.gouv.fr/_nuxt/D1qks5nO.js"
      },
      "link": "https://monsuivisocial.incubateur.anct.gouv.fr/_nuxt/D1qks5nO.js",
      "line": "--2024-07-21 01:29:11--  https://monsuivisocial.incubateur.anct.gouv.fr/_nuxt/D1qks5nO.js",
      "broken": false
    },
    {
      "url": {
        "protocol": "https:",
        "slashes": true,
        "auth": null,
        "host": "monsuivisocial.incubateur.anct.gouv.fr",
        "port": null,
        "hostname": "monsuivisocial.incubateur.anct.gouv.fr",
        "hash": null,
        "search": null,
        "query": null,
        "pathname": "/_nuxt/BvUvGLRp.js",
        "path": "/_nuxt/BvUvGLRp.js",
        "href": "https://monsuivisocial.incubateur.anct.gouv.fr/_nuxt/BvUvGLRp.js"
      },
      "link": "https://monsuivisocial.incubateur.anct.gouv.fr/_nuxt/BvUvGLRp.js",
      "line": "--2024-07-21 01:29:11--  https://monsuivisocial.incubateur.anct.gouv.fr/_nuxt/BvUvGLRp.js",
      "broken": false
    },
    {
      "url": {
        "protocol": "https:",
        "slashes": true,
        "auth": null,
        "host": "monsuivisocial.incubateur.anct.gouv.fr",
        "port": null,
        "hostname": "monsuivisocial.incubateur.anct.gouv.fr",
        "hash": null,
        "search": null,
        "query": null,
        "pathname": "/_nuxt/C7oi380W.js",
        "path": "/_nuxt/C7oi380W.js",
        "href": "https://monsuivisocial.incubateur.anct.gouv.fr/_nuxt/C7oi380W.js"
      },
      "link": "https://monsuivisocial.incubateur.anct.gouv.fr/_nuxt/C7oi380W.js",
      "line": "--2024-07-21 01:29:11--  https://monsuivisocial.incubateur.anct.gouv.fr/_nuxt/C7oi380W.js",
      "broken": false
    },
    {
      "url": {
        "protocol": "https:",
        "slashes": true,
        "auth": null,
        "host": "monsuivisocial.incubateur.anct.gouv.fr",
        "port": null,
        "hostname": "monsuivisocial.incubateur.anct.gouv.fr",
        "hash": null,
        "search": null,
        "query": null,
        "pathname": "/_nuxt/AtomModal.D24QuxII.css",
        "path": "/_nuxt/AtomModal.D24QuxII.css",
        "href": "https://monsuivisocial.incubateur.anct.gouv.fr/_nuxt/AtomModal.D24QuxII.css"
      },
      "link": "https://monsuivisocial.incubateur.anct.gouv.fr/_nuxt/AtomModal.D24QuxII.css",
      "line": "--2024-07-21 01:29:11--  https://monsuivisocial.incubateur.anct.gouv.fr/_nuxt/AtomModal.D24QuxII.css",
      "broken": false
    },
    {
      "url": {
        "protocol": "https:",
        "slashes": true,
        "auth": null,
        "host": "monsuivisocial.incubateur.anct.gouv.fr",
        "port": null,
        "hostname": "monsuivisocial.incubateur.anct.gouv.fr",
        "hash": null,
        "search": null,
        "query": null,
        "pathname": "/_nuxt/4M7qPouB.js",
        "path": "/_nuxt/4M7qPouB.js",
        "href": "https://monsuivisocial.incubateur.anct.gouv.fr/_nuxt/4M7qPouB.js"
      },
      "link": "https://monsuivisocial.incubateur.anct.gouv.fr/_nuxt/4M7qPouB.js",
      "line": "--2024-07-21 01:29:11--  https://monsuivisocial.incubateur.anct.gouv.fr/_nuxt/4M7qPouB.js",
      "broken": false
    },
    {
      "url": {
        "protocol": "https:",
        "slashes": true,
        "auth": null,
        "host": "monsuivisocial.incubateur.anct.gouv.fr",
        "port": null,
        "hostname": "monsuivisocial.incubateur.anct.gouv.fr",
        "hash": null,
        "search": null,
        "query": null,
        "pathname": "/_nuxt/sLIc2Q61.js",
        "path": "/_nuxt/sLIc2Q61.js",
        "href": "https://monsuivisocial.incubateur.anct.gouv.fr/_nuxt/sLIc2Q61.js"
      },
      "link": "https://monsuivisocial.incubateur.anct.gouv.fr/_nuxt/sLIc2Q61.js",
      "line": "--2024-07-21 01:29:11--  https://monsuivisocial.incubateur.anct.gouv.fr/_nuxt/sLIc2Q61.js",
      "broken": false
    },
    {
      "url": {
        "protocol": "https:",
        "slashes": true,
        "auth": null,
        "host": "monsuivisocial.incubateur.anct.gouv.fr",
        "port": null,
        "hostname": "monsuivisocial.incubateur.anct.gouv.fr",
        "hash": null,
        "search": null,
        "query": null,
        "pathname": "/_nuxt/CgIZsCmE.js",
        "path": "/_nuxt/CgIZsCmE.js",
        "href": "https://monsuivisocial.incubateur.anct.gouv.fr/_nuxt/CgIZsCmE.js"
      },
      "link": "https://monsuivisocial.incubateur.anct.gouv.fr/_nuxt/CgIZsCmE.js",
      "line": "--2024-07-21 01:29:11--  https://monsuivisocial.incubateur.anct.gouv.fr/_nuxt/CgIZsCmE.js",
      "broken": false
    },
    {
      "url": {
        "protocol": "https:",
        "slashes": true,
        "auth": null,
        "host": "monsuivisocial.incubateur.anct.gouv.fr",
        "port": null,
        "hostname": "monsuivisocial.incubateur.anct.gouv.fr",
        "hash": null,
        "search": null,
        "query": null,
        "pathname": "/_nuxt/CA3w2WBk.js",
        "path": "/_nuxt/CA3w2WBk.js",
        "href": "https://monsuivisocial.incubateur.anct.gouv.fr/_nuxt/CA3w2WBk.js"
      },
      "link": "https://monsuivisocial.incubateur.anct.gouv.fr/_nuxt/CA3w2WBk.js",
      "line": "--2024-07-21 01:29:11--  https://monsuivisocial.incubateur.anct.gouv.fr/_nuxt/CA3w2WBk.js",
      "broken": false
    },
    {
      "url": {
        "protocol": "https:",
        "slashes": true,
        "auth": null,
        "host": "monsuivisocial.incubateur.anct.gouv.fr",
        "port": null,
        "hostname": "monsuivisocial.incubateur.anct.gouv.fr",
        "hash": null,
        "search": null,
        "query": null,
        "pathname": "/_nuxt/BXefVoJf.js",
        "path": "/_nuxt/BXefVoJf.js",
        "href": "https://monsuivisocial.incubateur.anct.gouv.fr/_nuxt/BXefVoJf.js"
      },
      "link": "https://monsuivisocial.incubateur.anct.gouv.fr/_nuxt/BXefVoJf.js",
      "line": "--2024-07-21 01:29:11--  https://monsuivisocial.incubateur.anct.gouv.fr/_nuxt/BXefVoJf.js",
      "broken": false
    },
    {
      "url": {
        "protocol": "https:",
        "slashes": true,
        "auth": null,
        "host": "monsuivisocial.incubateur.anct.gouv.fr",
        "port": null,
        "hostname": "monsuivisocial.incubateur.anct.gouv.fr",
        "hash": null,
        "search": null,
        "query": null,
        "pathname": "/_nuxt/OdCUwABN.js",
        "path": "/_nuxt/OdCUwABN.js",
        "href": "https://monsuivisocial.incubateur.anct.gouv.fr/_nuxt/OdCUwABN.js"
      },
      "link": "https://monsuivisocial.incubateur.anct.gouv.fr/_nuxt/OdCUwABN.js",
      "line": "--2024-07-21 01:29:11--  https://monsuivisocial.incubateur.anct.gouv.fr/_nuxt/OdCUwABN.js",
      "broken": false
    },
    {
      "url": {
        "protocol": "https:",
        "slashes": true,
        "auth": null,
        "host": "monsuivisocial.incubateur.anct.gouv.fr",
        "port": null,
        "hostname": "monsuivisocial.incubateur.anct.gouv.fr",
        "hash": null,
        "search": null,
        "query": null,
        "pathname": "/_nuxt/logo.CRyEVgj8.svg",
        "path": "/_nuxt/logo.CRyEVgj8.svg",
        "href": "https://monsuivisocial.incubateur.anct.gouv.fr/_nuxt/logo.CRyEVgj8.svg"
      },
      "link": "https://monsuivisocial.incubateur.anct.gouv.fr/_nuxt/logo.CRyEVgj8.svg",
      "line": "--2024-07-21 01:29:12--  https://monsuivisocial.incubateur.anct.gouv.fr/_nuxt/logo.CRyEVgj8.svg",
      "broken": false
    },
    {
      "url": {
        "protocol": "https:",
        "slashes": true,
        "auth": null,
        "host": "monsuivisocial.incubateur.anct.gouv.fr",
        "port": null,
        "hostname": "monsuivisocial.incubateur.anct.gouv.fr",
        "hash": null,
        "search": null,
        "query": null,
        "pathname": "/_nuxt/logo-anct.D_A7fXcM.svg",
        "path": "/_nuxt/logo-anct.D_A7fXcM.svg",
        "href": "https://monsuivisocial.incubateur.anct.gouv.fr/_nuxt/logo-anct.D_A7fXcM.svg"
      },
      "link": "https://monsuivisocial.incubateur.anct.gouv.fr/_nuxt/logo-anct.D_A7fXcM.svg",
      "line": "--2024-07-21 01:29:12--  https://monsuivisocial.incubateur.anct.gouv.fr/_nuxt/logo-anct.D_A7fXcM.svg",
      "broken": false
    },
    {
      "url": {
        "protocol": "https:",
        "slashes": true,
        "auth": null,
        "host": "monsuivisocial.incubateur.anct.gouv.fr",
        "port": null,
        "hostname": "monsuivisocial.incubateur.anct.gouv.fr",
        "hash": null,
        "search": null,
        "query": null,
        "pathname": "/_nuxt/home-05.CMwKKYWP.svg",
        "path": "/_nuxt/home-05.CMwKKYWP.svg",
        "href": "https://monsuivisocial.incubateur.anct.gouv.fr/_nuxt/home-05.CMwKKYWP.svg"
      },
      "link": "https://monsuivisocial.incubateur.anct.gouv.fr/_nuxt/home-05.CMwKKYWP.svg",
      "line": "--2024-07-21 01:29:12--  https://monsuivisocial.incubateur.anct.gouv.fr/_nuxt/home-05.CMwKKYWP.svg",
      "broken": false
    },
    {
      "url": {
        "protocol": "https:",
        "slashes": true,
        "auth": null,
        "host": "monsuivisocial.incubateur.anct.gouv.fr",
        "port": null,
        "hostname": "monsuivisocial.incubateur.anct.gouv.fr",
        "hash": null,
        "search": null,
        "query": null,
        "pathname": "/_nuxt/video-presentation-preview.CjDdG5Bc.jpg",
        "path": "/_nuxt/video-presentation-preview.CjDdG5Bc.jpg",
        "href": "https://monsuivisocial.incubateur.anct.gouv.fr/_nuxt/video-presentation-preview.CjDdG5Bc.jpg"
      },
      "link": "https://monsuivisocial.incubateur.anct.gouv.fr/_nuxt/video-presentation-preview.CjDdG5Bc.jpg",
      "line": "--2024-07-21 01:29:12--  https://monsuivisocial.incubateur.anct.gouv.fr/_nuxt/video-presentation-preview.CjDdG5Bc.jpg",
      "broken": false
    },
    {
      "url": {
        "protocol": "https:",
        "slashes": true,
        "auth": null,
        "host": "monsuivisocial.incubateur.anct.gouv.fr",
        "port": null,
        "hostname": "monsuivisocial.incubateur.anct.gouv.fr",
        "hash": null,
        "search": null,
        "query": null,
        "pathname": "/_nuxt/presentation.CkvTCYP-.webm",
        "path": "/_nuxt/presentation.CkvTCYP-.webm",
        "href": "https://monsuivisocial.incubateur.anct.gouv.fr/_nuxt/presentation.CkvTCYP-.webm"
      },
      "link": "https://monsuivisocial.incubateur.anct.gouv.fr/_nuxt/presentation.CkvTCYP-.webm",
      "line": "--2024-07-21 01:29:12--  https://monsuivisocial.incubateur.anct.gouv.fr/_nuxt/presentation.CkvTCYP-.webm",
      "broken": false
    },
    {
      "url": {
        "protocol": "https:",
        "slashes": true,
        "auth": null,
        "host": "monsuivisocial.incubateur.anct.gouv.fr",
        "port": null,
        "hostname": "monsuivisocial.incubateur.anct.gouv.fr",
        "hash": null,
        "search": null,
        "query": null,
        "pathname": "/_nuxt/presentation.CfOKiD6J.mp4",
        "path": "/_nuxt/presentation.CfOKiD6J.mp4",
        "href": "https://monsuivisocial.incubateur.anct.gouv.fr/_nuxt/presentation.CfOKiD6J.mp4"
      },
      "link": "https://monsuivisocial.incubateur.anct.gouv.fr/_nuxt/presentation.CfOKiD6J.mp4",
      "line": "--2024-07-21 01:29:12--  https://monsuivisocial.incubateur.anct.gouv.fr/_nuxt/presentation.CfOKiD6J.mp4",
      "broken": false
    },
    {
      "url": {
        "protocol": "https:",
        "slashes": true,
        "auth": null,
        "host": "monsuivisocial.incubateur.anct.gouv.fr",
        "port": null,
        "hostname": "monsuivisocial.incubateur.anct.gouv.fr",
        "hash": null,
        "search": null,
        "query": null,
        "pathname": "/register",
        "path": "/register",
        "href": "https://monsuivisocial.incubateur.anct.gouv.fr/register"
      },
      "link": "https://monsuivisocial.incubateur.anct.gouv.fr/register",
      "line": "--2024-07-21 01:29:12--  https://monsuivisocial.incubateur.anct.gouv.fr/register",
      "broken": false
    },
    {
      "url": {
        "protocol": "https:",
        "slashes": true,
        "auth": null,
        "host": "monsuivisocial.incubateur.anct.gouv.fr",
        "port": null,
        "hostname": "monsuivisocial.incubateur.anct.gouv.fr",
        "hash": null,
        "search": null,
        "query": null,
        "pathname": "/auth/login",
        "path": "/auth/login",
        "href": "https://monsuivisocial.incubateur.anct.gouv.fr/auth/login"
      },
      "link": "https://monsuivisocial.incubateur.anct.gouv.fr/auth/login",
      "line": "--2024-07-21 01:29:13--  https://monsuivisocial.incubateur.anct.gouv.fr/auth/login",
      "broken": false
    },
    {
      "url": {
        "protocol": "https:",
        "slashes": true,
        "auth": null,
        "host": "monsuivisocial.incubateur.anct.gouv.fr",
        "port": null,
        "hostname": "monsuivisocial.incubateur.anct.gouv.fr",
        "hash": null,
        "search": null,
        "query": null,
        "pathname": "/~/assets/video/presentation.webm",
        "path": "/~/assets/video/presentation.webm",
        "href": "https://monsuivisocial.incubateur.anct.gouv.fr/~/assets/video/presentation.webm"
      },
      "link": "https://monsuivisocial.incubateur.anct.gouv.fr/~/assets/video/presentation.webm",
      "line": "--2024-07-21 01:29:13--  https://monsuivisocial.incubateur.anct.gouv.fr/~/assets/video/presentation.webm",
      "broken": false
    },
    {
      "url": {
        "protocol": "https:",
        "slashes": true,
        "auth": null,
        "host": "monsuivisocial.incubateur.anct.gouv.fr",
        "port": null,
        "hostname": "monsuivisocial.incubateur.anct.gouv.fr",
        "hash": null,
        "search": null,
        "query": null,
        "pathname": "/declaration-accessibilite",
        "path": "/declaration-accessibilite",
        "href": "https://monsuivisocial.incubateur.anct.gouv.fr/declaration-accessibilite"
      },
      "link": "https://monsuivisocial.incubateur.anct.gouv.fr/declaration-accessibilite",
      "line": "--2024-07-21 01:29:13--  https://monsuivisocial.incubateur.anct.gouv.fr/declaration-accessibilite",
      "broken": false
    },
    {
      "url": {
        "protocol": "https:",
        "slashes": true,
        "auth": null,
        "host": "monsuivisocial.incubateur.anct.gouv.fr",
        "port": null,
        "hostname": "monsuivisocial.incubateur.anct.gouv.fr",
        "hash": null,
        "search": null,
        "query": null,
        "pathname": "/mentions-legales",
        "path": "/mentions-legales",
        "href": "https://monsuivisocial.incubateur.anct.gouv.fr/mentions-legales"
      },
      "link": "https://monsuivisocial.incubateur.anct.gouv.fr/mentions-legales",
      "line": "--2024-07-21 01:29:14--  https://monsuivisocial.incubateur.anct.gouv.fr/mentions-legales",
      "broken": false
    },
    {
      "url": {
        "protocol": "https:",
        "slashes": true,
        "auth": null,
        "host": "monsuivisocial.incubateur.anct.gouv.fr",
        "port": null,
        "hostname": "monsuivisocial.incubateur.anct.gouv.fr",
        "hash": null,
        "search": null,
        "query": null,
        "pathname": "/statistiques",
        "path": "/statistiques",
        "href": "https://monsuivisocial.incubateur.anct.gouv.fr/statistiques"
      },
      "link": "https://monsuivisocial.incubateur.anct.gouv.fr/statistiques",
      "line": "--2024-07-21 01:29:14--  https://monsuivisocial.incubateur.anct.gouv.fr/statistiques",
      "broken": false
    },
    {
      "url": {
        "protocol": "https:",
        "slashes": true,
        "auth": null,
        "host": "monsuivisocial.incubateur.anct.gouv.fr",
        "port": null,
        "hostname": "monsuivisocial.incubateur.anct.gouv.fr",
        "hash": null,
        "search": null,
        "query": null,
        "pathname": "/_nuxt/C14cpzzf.js",
        "path": "/_nuxt/C14cpzzf.js",
        "href": "https://monsuivisocial.incubateur.anct.gouv.fr/_nuxt/C14cpzzf.js"
      },
      "link": "https://monsuivisocial.incubateur.anct.gouv.fr/_nuxt/C14cpzzf.js",
      "line": "--2024-07-21 01:29:14--  https://monsuivisocial.incubateur.anct.gouv.fr/_nuxt/C14cpzzf.js",
      "broken": false
    },
    {
      "url": {
        "protocol": "https:",
        "slashes": true,
        "auth": null,
        "host": "monsuivisocial.incubateur.anct.gouv.fr",
        "port": null,
        "hostname": "monsuivisocial.incubateur.anct.gouv.fr",
        "hash": null,
        "search": null,
        "query": null,
        "pathname": "/_nuxt/register-01.BhPdWCw8.svg",
        "path": "/_nuxt/register-01.BhPdWCw8.svg",
        "href": "https://monsuivisocial.incubateur.anct.gouv.fr/_nuxt/register-01.BhPdWCw8.svg"
      },
      "link": "https://monsuivisocial.incubateur.anct.gouv.fr/_nuxt/register-01.BhPdWCw8.svg",
      "line": "--2024-07-21 01:29:14--  https://monsuivisocial.incubateur.anct.gouv.fr/_nuxt/register-01.BhPdWCw8.svg",
      "broken": false
    },
    {
      "url": {
        "protocol": "https:",
        "slashes": true,
        "auth": null,
        "host": "monsuivisocial.incubateur.anct.gouv.fr",
        "port": null,
        "hostname": "monsuivisocial.incubateur.anct.gouv.fr",
        "hash": null,
        "search": null,
        "query": null,
        "pathname": "/_nuxt/register-02.zelAPWqk.svg",
        "path": "/_nuxt/register-02.zelAPWqk.svg",
        "href": "https://monsuivisocial.incubateur.anct.gouv.fr/_nuxt/register-02.zelAPWqk.svg"
      },
      "link": "https://monsuivisocial.incubateur.anct.gouv.fr/_nuxt/register-02.zelAPWqk.svg",
      "line": "--2024-07-21 01:29:14--  https://monsuivisocial.incubateur.anct.gouv.fr/_nuxt/register-02.zelAPWqk.svg",
      "broken": false
    },
    {
      "url": {
        "protocol": "https:",
        "slashes": true,
        "auth": null,
        "host": "monsuivisocial.incubateur.anct.gouv.fr",
        "port": null,
        "hostname": "monsuivisocial.incubateur.anct.gouv.fr",
        "hash": null,
        "search": null,
        "query": null,
        "pathname": "/_nuxt/register-03.DCshSM0g.svg",
        "path": "/_nuxt/register-03.DCshSM0g.svg",
        "href": "https://monsuivisocial.incubateur.anct.gouv.fr/_nuxt/register-03.DCshSM0g.svg"
      },
      "link": "https://monsuivisocial.incubateur.anct.gouv.fr/_nuxt/register-03.DCshSM0g.svg",
      "line": "--2024-07-21 01:29:14--  https://monsuivisocial.incubateur.anct.gouv.fr/_nuxt/register-03.DCshSM0g.svg",
      "broken": false
    },
    {
      "url": {
        "protocol": "https:",
        "slashes": true,
        "auth": null,
        "host": "monsuivisocial.incubateur.anct.gouv.fr",
        "port": null,
        "hostname": "monsuivisocial.incubateur.anct.gouv.fr",
        "hash": null,
        "search": null,
        "query": null,
        "pathname": "/_nuxt/InclusionConnectButton.CnHXUx3e.css",
        "path": "/_nuxt/InclusionConnectButton.CnHXUx3e.css",
        "href": "https://monsuivisocial.incubateur.anct.gouv.fr/_nuxt/InclusionConnectButton.CnHXUx3e.css"
      },
      "link": "https://monsuivisocial.incubateur.anct.gouv.fr/_nuxt/InclusionConnectButton.CnHXUx3e.css",
      "line": "--2024-07-21 01:29:14--  https://monsuivisocial.incubateur.anct.gouv.fr/_nuxt/InclusionConnectButton.CnHXUx3e.css",
      "broken": false
    },
    {
      "url": {
        "protocol": "https:",
        "slashes": true,
        "auth": null,
        "host": "monsuivisocial.incubateur.anct.gouv.fr",
        "port": null,
        "hostname": "monsuivisocial.incubateur.anct.gouv.fr",
        "hash": null,
        "search": null,
        "query": null,
        "pathname": "/_nuxt/B4hCKhM5.js",
        "path": "/_nuxt/B4hCKhM5.js",
        "href": "https://monsuivisocial.incubateur.anct.gouv.fr/_nuxt/B4hCKhM5.js"
      },
      "link": "https://monsuivisocial.incubateur.anct.gouv.fr/_nuxt/B4hCKhM5.js",
      "line": "--2024-07-21 01:29:15--  https://monsuivisocial.incubateur.anct.gouv.fr/_nuxt/B4hCKhM5.js",
      "broken": false
    },
    {
      "url": {
        "protocol": "https:",
        "slashes": true,
        "auth": null,
        "host": "monsuivisocial.incubateur.anct.gouv.fr",
        "port": null,
        "hostname": "monsuivisocial.incubateur.anct.gouv.fr",
        "hash": null,
        "search": null,
        "query": null,
        "pathname": "/_nuxt/DVN29u49.js",
        "path": "/_nuxt/DVN29u49.js",
        "href": "https://monsuivisocial.incubateur.anct.gouv.fr/_nuxt/DVN29u49.js"
      },
      "link": "https://monsuivisocial.incubateur.anct.gouv.fr/_nuxt/DVN29u49.js",
      "line": "--2024-07-21 01:29:15--  https://monsuivisocial.incubateur.anct.gouv.fr/_nuxt/DVN29u49.js",
      "broken": false
    },
    {
      "url": {
        "protocol": "https:",
        "slashes": true,
        "auth": null,
        "host": "monsuivisocial.incubateur.anct.gouv.fr",
        "port": null,
        "hostname": "monsuivisocial.incubateur.anct.gouv.fr",
        "hash": null,
        "search": null,
        "query": null,
        "pathname": "/api/keycloak/signin",
        "path": "/api/keycloak/signin",
        "href": "https://monsuivisocial.incubateur.anct.gouv.fr/api/keycloak/signin"
      },
      "link": "https://monsuivisocial.incubateur.anct.gouv.fr/api/keycloak/signin",
      "line": "--2024-07-21 01:29:15--  https://monsuivisocial.incubateur.anct.gouv.fr/api/keycloak/signin",
      "broken": false
    },
    {
      "url": {
        "protocol": "https:",
        "slashes": true,
        "auth": null,
        "host": "connect.inclusion.beta.gouv.fr",
        "port": null,
        "hostname": "connect.inclusion.beta.gouv.fr",
        "hash": null,
        "search": "?client_id=monsuivisocial&scope=openid+profile+email&response_type=code&redirect_uri=https%3A%2F%2Fmonsuivisocial.incubateur.anct.gouv.fr%2Fapi%2Fkeycloak%2Fcallback&state=nGv5NlQP8agmQ81DnDOMVDOtXeKdOHjfgH4LJc46YPA&nonce=nGv5NlQP8agmQ81DnDOMVDOtXeKdOHjfgH4LJc46YPA",
        "query": "client_id=monsuivisocial&scope=openid+profile+email&response_type=code&redirect_uri=https%3A%2F%2Fmonsuivisocial.incubateur.anct.gouv.fr%2Fapi%2Fkeycloak%2Fcallback&state=nGv5NlQP8agmQ81DnDOMVDOtXeKdOHjfgH4LJc46YPA&nonce=nGv5NlQP8agmQ81DnDOMVDOtXeKdOHjfgH4LJc46YPA",
        "pathname": "/auth/authorize/",
        "path": "/auth/authorize/?client_id=monsuivisocial&scope=openid+profile+email&response_type=code&redirect_uri=https%3A%2F%2Fmonsuivisocial.incubateur.anct.gouv.fr%2Fapi%2Fkeycloak%2Fcallback&state=nGv5NlQP8agmQ81DnDOMVDOtXeKdOHjfgH4LJc46YPA&nonce=nGv5NlQP8agmQ81DnDOMVDOtXeKdOHjfgH4LJc46YPA",
        "href": "https://connect.inclusion.beta.gouv.fr/auth/authorize/?client_id=monsuivisocial&scope=openid+profile+email&response_type=code&redirect_uri=https%3A%2F%2Fmonsuivisocial.incubateur.anct.gouv.fr%2Fapi%2Fkeycloak%2Fcallback&state=nGv5NlQP8agmQ81DnDOMVDOtXeKdOHjfgH4LJc46YPA&nonce=nGv5NlQP8agmQ81DnDOMVDOtXeKdOHjfgH4LJc46YPA"
      },
      "link": "https://connect.inclusion.beta.gouv.fr/auth/authorize/?client_id=monsuivisocial&scope=openid+profile+email&response_type=code&redirect_uri=https%3A%2F%2Fmonsuivisocial.incubateur.anct.gouv.fr%2Fapi%2Fkeycloak%2Fcallback&state=nGv5NlQP8agmQ81DnDOMVDOtXeKdOHjfgH4LJc46YPA&nonce=nGv5NlQP8agmQ81DnDOMVDOtXeKdOHjfgH4LJc46YPA",
      "line": "--2024-07-21 01:29:15--  https://connect.inclusion.beta.gouv.fr/auth/authorize/?client_id=monsuivisocial&scope=openid+profile+email&response_type=code&redirect_uri=https%3A%2F%2Fmonsuivisocial.incubateur.anct.gouv.fr%2Fapi%2Fkeycloak%2Fcallback&state=nGv5NlQP8agmQ81DnDOMVDOtXeKdOHjfgH4LJc46YPA&nonce=nGv5NlQP8agmQ81DnDOMVDOtXeKdOHjfgH4LJc46YPA",
      "broken": false
    },
    {
      "url": {
        "protocol": "https:",
        "slashes": true,
        "auth": null,
        "host": "connect.inclusion.beta.gouv.fr",
        "port": null,
        "hostname": "connect.inclusion.beta.gouv.fr",
        "hash": null,
        "search": null,
        "query": null,
        "pathname": "/accounts/login/",
        "path": "/accounts/login/",
        "href": "https://connect.inclusion.beta.gouv.fr/accounts/login/"
      },
      "link": "https://connect.inclusion.beta.gouv.fr/accounts/login/",
      "line": "--2024-07-21 01:29:15--  https://connect.inclusion.beta.gouv.fr/accounts/login/",
      "broken": false
    },
    {
      "url": {
        "protocol": "https:",
        "slashes": true,
        "auth": null,
        "host": "monsuivisocial.incubateur.anct.gouv.fr",
        "port": null,
        "hostname": "monsuivisocial.incubateur.anct.gouv.fr",
        "hash": null,
        "search": null,
        "query": null,
        "pathname": "/_nuxt/c7CVH6LD.js",
        "path": "/_nuxt/c7CVH6LD.js",
        "href": "https://monsuivisocial.incubateur.anct.gouv.fr/_nuxt/c7CVH6LD.js"
      },
      "link": "https://monsuivisocial.incubateur.anct.gouv.fr/_nuxt/c7CVH6LD.js",
      "line": "--2024-07-21 01:29:16--  https://monsuivisocial.incubateur.anct.gouv.fr/_nuxt/c7CVH6LD.js",
      "broken": false
    },
    {
      "url": {
        "protocol": "https:",
        "slashes": true,
        "auth": null,
        "host": "monsuivisocial.incubateur.anct.gouv.fr",
        "port": null,
        "hostname": "monsuivisocial.incubateur.anct.gouv.fr",
        "hash": null,
        "search": null,
        "query": null,
        "pathname": "/_nuxt/BHFhrJwb.js",
        "path": "/_nuxt/BHFhrJwb.js",
        "href": "https://monsuivisocial.incubateur.anct.gouv.fr/_nuxt/BHFhrJwb.js"
      },
      "link": "https://monsuivisocial.incubateur.anct.gouv.fr/_nuxt/BHFhrJwb.js",
      "line": "--2024-07-21 01:29:16--  https://monsuivisocial.incubateur.anct.gouv.fr/_nuxt/BHFhrJwb.js",
      "broken": false
    },
    {
      "url": {
        "protocol": "https:",
        "slashes": true,
        "auth": null,
        "host": "monsuivisocial.incubateur.anct.gouv.fr",
        "port": null,
        "hostname": "monsuivisocial.incubateur.anct.gouv.fr",
        "hash": null,
        "search": null,
        "query": null,
        "pathname": "/_nuxt/BzZQna8H.js",
        "path": "/_nuxt/BzZQna8H.js",
        "href": "https://monsuivisocial.incubateur.anct.gouv.fr/_nuxt/BzZQna8H.js"
      },
      "link": "https://monsuivisocial.incubateur.anct.gouv.fr/_nuxt/BzZQna8H.js",
      "line": "--2024-07-21 01:29:16--  https://monsuivisocial.incubateur.anct.gouv.fr/_nuxt/BzZQna8H.js",
      "broken": false
    }
  ],
  "broken": []
}