{
  "trackers": [
    {
      "type": "unknown",
      "url": "https://js.hcaptcha.com/1/api.js"
    }
  ],
  "cookies": [
    {
      "name": "_pk_ses.147.204e",
      "value": "1",
      "domain": "www.conseiller-numerique.gouv.fr",
      "path": "/",
      "expires": 1729389125,
      "size": 17,
      "httpOnly": false,
      "secure": false,
      "session": false,
      "sameSite": "Lax",
      "sameParty": false,
      "sourceScheme": "Secure",
      "sourcePort": 443
    },
    {
      "name": "_pk_id.147.204e",
      "value": "b88cc4bdb5110142.1729387325.",
      "domain": "www.conseiller-numerique.gouv.fr",
      "path": "/",
      "expires": 1763342525,
      "size": 43,
      "httpOnly": false,
      "secure": false,
      "session": false,
      "sameSite": "Lax",
      "sameParty": false,
      "sourceScheme": "Secure",
      "sourcePort": 443
    }
  ],
  "headers": {
    "alt-svc": "h3=\":443\"; ma=86400",
    "cache-control": "max-age=60, private, proxy-revalidate",
    "cf-cache-status": "DYNAMIC",
    "cf-ray": "8d5531dbae85c994-IAD",
    "content-encoding": "br",
    "content-type": "text/html",
    "date": "Sun, 20 Oct 2024 01:22:04 GMT",
    "last-modified": "Mon, 14 Oct 2024 13:34:18 GMT",
    "nel": "{\"success_fraction\":0,\"report_to\":\"cf-nel\",\"max_age\":604800}",
    "report-to": "{\"endpoints\":[{\"url\":\"https:\\/\\/a.nel.cloudflare.com\\/report\\/v4?s=P5Ubmh%2FZpN89bl7u0o3EKaKyFE%2FbS8dxpNLPhYswTdsi8X7WVXhSER2K6Q9qWPDRTMXgHp8rmQ%2FLhuiHxL1dA95mnvIz%2BG8e92aaXrKGbKMEfC4vZFgDSlEk0KMfQYSh5XtWMX65vFZzoSdz4%2F99wFGkyQ%3D%3D\"}],\"group\":\"cf-nel\",\"max_age\":604800}",
    "server": "cloudflare",
    "server-timing": "cfL4;desc=\"?proto=TCP&rtt=10851&sent=6&recv=9&lost=0&retrans=0&sent_bytes=2843&recv_bytes=1072&delivery_rate=531546&cwnd=253&unsent_bytes=0&cid=56e57608349767fa&ts=110&x=0\"",
    "sozu-id": "01JAKR82MQWY7HFMAN89PNVWWV",
    "vary": "Accept-Encoding"
  },
  "endpoints": [
    {
      "hostname": "www.conseiller-numerique.gouv.fr",
      "ip": "104.21.71.120",
      "geoip": {
        "registered_country": {
          "geoname_id": 6252001,
          "iso_code": "US",
          "names": {
            "de": "USA",
            "en": "United States",
            "es": "Estados Unidos",
            "fr": "États Unis",
            "ja": "アメリカ",
            "pt-BR": "EUA",
            "ru": "США",
            "zh-CN": "美国"
          }
        }
      }
    },
    {
      "hostname": "js.hcaptcha.com",
      "ip": "104.19.229.21",
      "geoip": {
        "registered_country": {
          "geoname_id": 6252001,
          "iso_code": "US",
          "names": {
            "de": "USA",
            "en": "United States",
            "es": "Estados Unidos",
            "fr": "États Unis",
            "ja": "アメリカ",
            "pt-BR": "EUA",
            "ru": "США",
            "zh-CN": "美国"
          }
        }
      }
    }
  ]
}
