{
  "scan": {
    "algorithmVersion": 4,
    "grade": "B",
    "error": null,
    "score": 75,
    "statusCode": 200,
    "testsFailed": 1,
    "testsPassed": 9,
    "testsQuantity": 10,
    "responseHeaders": {
      "date": "Sun, 18 May 2025 01:54:27 GMT",
      "content-type": "text/html; charset=utf-8",
      "content-length": "5983",
      "connection": "close",
      "x-frame-options": "SAMEORIGIN",
      "x-xss-protection": "0",
      "x-content-type-options": "nosniff",
      "x-download-options": "noopen",
      "x-permitted-cross-domain-policies": "none",
      "referrer-policy": "strict-origin-when-cross-origin",
      "link": "</packs/css/application-1b36d1b4.css>; rel=preload; as=style; nopush",
      "vary": "Accept-Encoding",
      "etag": "W/\"ff4df10bf86cabc3a2ad5217c1f91d6c\"",
      "cache-control": "max-age=0, private, must-revalidate",
      "set-cookie": [
        "_monstage_session=YeYw70E%2FR03hHH1sm4tmkLgKKfklWFpAMIQ4jNjXKVPR90hDw4dQqOENMmIS4ay0TCWAsnaTGQdlzd727wltDMqArV6xAgd5v3fyul%2BrTOYOwPN7u2I3YRa7sflazb19iDyho30TEV%2B99rE7T93jnrR8E11YPNWR1b4EfOvYAOgxXMhORVZfHDWvbtC%2BFYPxS818mnnEnSNt4N5Fsa0Sbrc3mOBiBsmimxYmlJptaUx70%2F9zYRi0u1Jnx%2FFr1uqCeSsnEnIRDYxenM9quOGGp06qdkgx04QmxA%3D%3D--GeuNrDz4v513j1FZ--qTZMFA92u595Lk3qTpnYNA%3D%3D; path=/; secure; HttpOnly; SameSite=Lax"
      ],
      "x-request-id": "688bba57-47fe-4a14-93fd-2ca0d9322ebe",
      "x-runtime": "0.006778",
      "strict-transport-security": "max-age=63072000; includeSubDomains",
      "sozu-id": "01JVGHK00RM120NFR0G3YGY07Z"
    }
  },
  "tests": {
    "content-security-policy": {
      "expectation": "csp-implemented-with-no-unsafe",
      "pass": false,
      "result": "csp-not-implemented",
      "scoreModifier": -25,
      "data": null,
      "http": false,
      "meta": false,
      "policy": null,
      "numPolicies": 0
    },
    "cookies": {
      "expectation": "cookies-secure-with-httponly-sessions",
      "pass": true,
      "result": "cookies-secure-with-httponly-sessions-and-samesite",
      "scoreModifier": 5,
      "data": {
        "_monstage_session": {
          "domain": "www.monstagedetroisieme.fr",
          "httponly": true,
          "path": "/",
          "port": null,
          "samesite": "lax",
          "secure": true
        }
      },
      "sameSite": true
    },
    "cross-origin-resource-sharing": {
      "expectation": "cross-origin-resource-sharing-not-implemented",
      "pass": true,
      "result": "cross-origin-resource-sharing-not-implemented",
      "scoreModifier": 0,
      "data": null
    },
    "redirection": {
      "expectation": "redirection-to-https",
      "pass": true,
      "result": "redirection-to-https",
      "scoreModifier": 0,
      "destination": "https://www.monstagedetroisieme.fr/",
      "redirects": true,
      "route": [
        "http://www.monstagedetroisieme.fr/",
        "https://www.monstagedetroisieme.fr/"
      ],
      "statusCode": 200
    },
    "referrer-policy": {
      "expectation": "referrer-policy-private",
      "pass": true,
      "result": "referrer-policy-private",
      "scoreModifier": 5,
      "data": "strict-origin-when-cross-origin",
      "http": true,
      "meta": false
    },
    "strict-transport-security": {
      "expectation": "hsts-implemented-max-age-at-least-six-months",
      "pass": true,
      "result": "hsts-implemented-max-age-at-least-six-months",
      "scoreModifier": 0,
      "data": "max-age=63072000; includeSubDomains",
      "includeSubDomains": true,
      "maxAge": 63072000,
      "preload": false,
      "preloaded": false
    },
    "subresource-integrity": {
      "expectation": "sri-implemented-and-external-scripts-loaded-securely",
      "pass": true,
      "result": "sri-not-implemented-but-all-scripts-loaded-from-secure-origin",
      "scoreModifier": 0,
      "data": {}
    },
    "x-content-type-options": {
      "expectation": "x-content-type-options-nosniff",
      "pass": true,
      "result": "x-content-type-options-nosniff",
      "scoreModifier": 0,
      "data": "nosniff"
    },
    "x-frame-options": {
      "expectation": "x-frame-options-sameorigin-or-deny",
      "pass": true,
      "result": "x-frame-options-sameorigin-or-deny",
      "scoreModifier": 0,
      "data": "SAMEORIGIN"
    },
    "cross-origin-resource-policy": {
      "expectation": "corp-implemented-with-same-site",
      "pass": true,
      "result": "corp-not-implemented",
      "scoreModifier": 0,
      "data": null,
      "http": false,
      "meta": false
    }
  }
}
